Metadata-Version: 1.0
Name: dndy-distributions
Version: 0.1
Summary: Gaussian distributions
Home-page: UNKNOWN
Author: Clera Gan
Author-email: UNKNOWN
License: UNKNOWN
Platform: UNKNOWN
